[
  {
    "anonymous": false,
    "inputs": [
      {
        "indexed": false,
        "internalType": "address",
        "name": "keeperAddress",
        "type": "address"
      }
    ],
    "name": "KeeperCreated",
    "type": "event"
  },
  {
    "anonymous": false,
    "inputs": [
      {
        "indexed": false,
        "internalType": "address",
        "name": "marketAddress",
        "type": "address"
      },
      {
        "indexed": false,
        "internalType": "address",
        "name": "keeperAddress",
        "type": "address"
      }
    ],
    "name": "MarketCreated",
    "type": "event"
  },
  {
    "inputs": [
      {
        "internalType": "address",
        "name": "oracleAddress",
        "type": "address"
      },
      {
        "internalType": "enum IOracle.Type",
        "name": "oracleType",
        "type": "uint8"
      }
    ],
    "name": "addOracleAddress",
    "outputs": [],
    "stateMutability": "nonpayable",
    "type": "function"
  },
  {
    "inputs": [],
    "name": "allMarketsLength",
    "outputs": [
      {
        "internalType": "uint256",
        "name": "",
        "type": "uint256"
      }
    ],
    "stateMutability": "view",
    "type": "function"
  },
  {
    "inputs": [
      {
        "components": [
          {
            "internalType": "string",
            "name": "name",
            "type": "string"
          }
        ],
        "internalType": "struct IAmmDeployer.Parameters",
        "name": "params",
        "type": "tuple"
      }
    ],
    "name": "createAmm",
    "outputs": [
      {
        "internalType": "address",
        "name": "amm",
        "type": "address"
      }
    ],
    "stateMutability": "nonpayable",
    "type": "function"
  },
  {
    "inputs": [
      {
        "components": [
          {
            "internalType": "string",
            "name": "underlyingAssetName",
            "type": "string"
          },
          {
            "internalType": "address",
            "name": "coin",
            "type": "address"
          },
          {
            "internalType": "uint256",
            "name": "duration",
            "type": "uint256"
          },
          {
            "internalType": "address",
            "name": "oracleAggregatorAddress",
            "type": "address"
          },
          {
            "internalType": "enum IOracle.Type",
            "name": "oracleType",
            "type": "uint8"
          },
          {
            "internalType": "uint256",
            "name": "operatorFee",
            "type": "uint256"
          },
          {
            "internalType": "uint256",
            "name": "serviceFee",
            "type": "uint256"
          }
        ],
        "internalType": "struct IFactory.MarketParams",
        "name": "params",
        "type": "tuple"
      }
    ],
    "name": "createMarket",
    "outputs": [
      {
        "internalType": "address",
        "name": "market",
        "type": "address"
      }
    ],
    "stateMutability": "nonpayable",
    "type": "function"
  },
  {
    "inputs": [],
    "name": "depositAddress",
    "outputs": [
      {
        "internalType": "address",
        "name": "",
        "type": "address"
      }
    ],
    "stateMutability": "nonpayable",
    "type": "function"
  },
  {
    "inputs": [
      {
        "internalType": "enum IOracle.Type",
        "name": "oracleType",
        "type": "uint8"
      }
    ],
    "name": "getOracleAddress",
    "outputs": [
      {
        "internalType": "address",
        "name": "",
        "type": "address"
      }
    ],
    "stateMutability": "nonpayable",
    "type": "function"
  },
  {
    "inputs": [],
    "name": "getOwner",
    "outputs": [
      {
        "internalType": "address",
        "name": "",
        "type": "address"
      }
    ],
    "stateMutability": "view",
    "type": "function"
  },
  {
    "inputs": [
      {
        "internalType": "address",
        "name": "",
        "type": "address"
      }
    ],
    "name": "isMarket",
    "outputs": [
      {
        "internalType": "bool",
        "name": "",
        "type": "bool"
      }
    ],
    "stateMutability": "nonpayable",
    "type": "function"
  },
  {
    "inputs": [
      {
        "internalType": "address",
        "name": "depositAddress_",
        "type": "address"
      }
    ],
    "name": "setDeposit",
    "outputs": [],
    "stateMutability": "nonpayable",
    "type": "function"
  },
  {
    "inputs": [
      {
        "internalType": "address",
        "name": "storageAddress_",
        "type": "address"
      }
    ],
    "name": "setStorage",
    "outputs": [],
    "stateMutability": "nonpayable",
    "type": "function"
  },
  {
    "inputs": [],
    "name": "storageAddress",
    "outputs": [
      {
        "internalType": "address",
        "name": "",
        "type": "address"
      }
    ],
    "stateMutability": "nonpayable",
    "type": "function"
  }
]
